ascend_nputop-0.0.4.dist-info/licenses/COPYING
ascend_nputop-0.0.4.dist-info/licenses/LICENSE
ascend_nputop-0.0.4.dist-info/licenses/NOTICE
nputop/__init__.py
nputop/__main__.py
nputop/cli.py
nputop/select.py
nputop/version.py
nputop/api/__init__.py
nputop/api/collector.py
nputop/api/device.py
nputop/api/host.py
nputop/api/libascend.py
nputop/api/process.py
nputop/api/utils.py
nputop/gui/__init__.py
nputop/gui/ui.py
nputop/gui/library/__init__.py
nputop/gui/library/device.py
nputop/gui/library/displayable.py
nputop/gui/library/history.py
nputop/gui/library/keybinding.py
nputop/gui/library/libcurses.py
nputop/gui/library/messagebox.py
nputop/gui/library/mouse.py
nputop/gui/library/process.py
nputop/gui/library/selection.py
nputop/gui/library/utils.py
nputop/gui/library/widestring.py
nputop/gui/screens/__init__.py
nputop/gui/screens/environ.py
nputop/gui/screens/help.py
nputop/gui/screens/metrics.py
nputop/gui/screens/treeview.py
nputop/gui/screens/main/__init__.py
nputop/gui/screens/main/device.py
nputop/gui/screens/main/host.py
nputop/gui/screens/main/process.py
ascend_nputop-0.0.4.dist-info/METADATA
ascend_nputop-0.0.4.dist-info/WHEEL
ascend_nputop-0.0.4.dist-info/entry_points.txt
ascend_nputop-0.0.4.dist-info/top_level.txt
ascend_nputop-0.0.4.dist-info/RECORD
