Metadata-Version: 2.4
Name: ascend-nputop
Version: 0.0.4
Summary: An interactive Ascend-NPU process viewer.
Author: Lianzhong You
Author-email: Lianzhong You <youlianzhong@gml.ac.cn>
License: Apache License, Version 2.0 (Apache-2.0) & GNU General Public License, Version 3 (GPL-3.0)
Project-URL: Homepage, https://github.com/youyve/nputop
Project-URL: Repository, https://github.com/youyve/nputop
Project-URL: Documentation, https://nputop.readthedocs.io
Project-URL: Bug Report, https://github.com/youyve/nputop/issues
Keywords: ascend,npu-smi,Ascend,pyacl,NPU,top,monitoring
Classifier: Development Status :: 5 - Production/Stable
Classifier: License :: OSI Approved :: Apache Software License
Classifier: License :: OSI Approved :: GNU General Public License v3 (GPLv3)
Classifier: Programming Language :: Python :: 3
Classifier: Programming Language :: Python :: 3.7
Classifier: Programming Language :: Python :: 3.8
Classifier: Programming Language :: Python :: 3.9
Classifier: Programming Language :: Python :: 3.10
Classifier: Programming Language :: Python :: 3.11
Classifier: Programming Language :: Python :: 3.12
Classifier: Operating System :: Microsoft :: Windows
Classifier: Operating System :: POSIX :: Linux
Classifier: Environment :: Console
Classifier: Environment :: Console :: Curses
Classifier: Intended Audience :: Developers
Classifier: Intended Audience :: End Users/Desktop
Classifier: Intended Audience :: System Administrators
Classifier: Topic :: System :: Hardware
Classifier: Topic :: System :: Monitoring
Classifier: Topic :: System :: Systems Administration
Classifier: Topic :: Utilities
Requires-Python: >=3.7
License-File: LICENSE
License-File: COPYING
License-File: NOTICE
Requires-Dist: psutil>=5.6.6
Requires-Dist: cachetools>=1.0.1
Requires-Dist: termcolor>=1.0.0
Requires-Dist: colorama>=0.4.0; platform_system == "Windows"
Requires-Dist: windows-curses>=2.2.0; platform_system == "Windows"
Provides-Extra: lint
Requires-Dist: black<25.0.0a0,>=24.0.0; extra == "lint"
Requires-Dist: isort; extra == "lint"
Requires-Dist: pylint[spelling]; extra == "lint"
Requires-Dist: mypy; extra == "lint"
Requires-Dist: typing-extensions; extra == "lint"
Requires-Dist: pre-commit; extra == "lint"
Provides-Extra: cuda10
Requires-Dist: nvidia-ml-py==11.450.51; extra == "cuda10"
Dynamic: author
Dynamic: license-file
Dynamic: provides-extra
Dynamic: requires-python
